larch_reactive-4.0.12.dist-info/RECORD
larch_reactive-4.0.12.dist-info/LICENSE
larch_reactive-4.0.12.dist-info/WHEEL
larch_reactive-4.0.12.dist-info/top_level.txt
larch_reactive-4.0.12.dist-info/METADATA
larch/reactive/exception.py
larch/reactive/version.py
larch/reactive/rcollections.py
larch/reactive/_handler.py
larch/reactive/proxy.py
larch/reactive/cell.py
larch/reactive/ccore.pyx
larch/reactive/pcore.py
larch/reactive/pyref.h
larch/reactive/__init__.py
larch/reactive/core.py
larch/reactive/debug.py
larch/reactive/greenlet.h
larch/reactive/agent.py
larch/reactive/ccore.cpp
larch/reactive/pointer.py
larch/reactive/ccore.cpython-311-darwin.so
larch/reactive/base.py
