Metadata-Version: 2.1
Name: larch-reactive
Version: 4.0.12
Summary: reactive programming for python
Home-page: https://github.com/kochelmonster/larch-reactive
Author: Michael Reithinger
Author-email: Michael Reithinger <mreithinger@web.de>
License: BSD
Keywords: library
Classifier: Development Status :: 5 - Production/Stable
Classifier: Intended Audience :: Developers
Classifier: License :: OSI Approved :: BSD License
Classifier: Programming Language :: Python :: 3
Classifier: Topic :: Software Development :: Libraries :: Python Modules
Provides-Extra: build
Provides-Extra: documentation
License-File: LICENSE
